otelmark/__init__.py
otelmark/_collections.py
otelmark/_collector.py
otelmark/_constants.py
otelmark/_otelmark.py
otelmark/_span.py
otelmark/_utils.py
otelmark/py.typed
otelmark/testing.py
otelmark-0.1.0a0.dist-info/licenses/LICENSE
otelmark-0.1.0a0.dist-info/WHEEL
otelmark-0.1.0a0.dist-info/METADATA
otelmark-0.1.0a0.dist-info/RECORD
